boto3_fixtures/__init__.py
boto3_fixtures/_version.py
boto3_fixtures/awslambda.py
boto3_fixtures/dynamodb.py
boto3_fixtures/exceptions.py
boto3_fixtures/kinesis.py
boto3_fixtures/s3.py
boto3_fixtures/service.py
boto3_fixtures/sns.py
boto3_fixtures/sqs.py
boto3_fixtures/utils.py
boto3_fixtures/contrib/__init__.py
boto3_fixtures/contrib/boto3.py
boto3_fixtures/contrib/mindictive.py
boto3_fixtures/contrib/pytest.py
boto3_fixtures/contrib/sqs.py
dummy_lambda/func/__init__.py
dummy_lambda/func/main.py
boto3_fixtures-0.0.8.dist-info/LICENSE
boto3_fixtures-0.0.8.dist-info/METADATA
boto3_fixtures-0.0.8.dist-info/WHEEL
boto3_fixtures-0.0.8.dist-info/entry_points.txt
boto3_fixtures-0.0.8.dist-info/top_level.txt
boto3_fixtures-0.0.8.dist-info/RECORD
