Metadata-Version: 2.1
Name: boto3-fixtures
Version: 0.0.8
Summary: Python test fixtures for your local AWS cloud stack
Home-page: https://github.com/alphachai/boto3-fixtures
Author: Charlie Mathews
Author-email: charlie@charliemathews.com
Maintainer: Charlie Mathews
Maintainer-email: charlie@charliemathews.com
License: APACHE
Project-URL: Bug Tracker, https://github.com/alphachai/boto3-fixtures/issues
Project-URL: Source Code, https://github.com/alphachai/boto3-fixtures
Platform: UNKNOWN
Classifier: Development Status :: 5 - Production/Stable
Classifier: Intended Audience :: Developers
Classifier: Topic :: Software Development :: Testing
Classifier: Programming Language :: Python :: 3
Classifier: Programming Language :: Python :: 3.6
Classifier: Programming Language :: Python :: 3.7
Classifier: Programming Language :: Python :: 3.8
Classifier: Operating System :: OS Independent
Classifier: License :: OSI Approved :: Apache Software License
Classifier: Framework :: Pytest
Requires-Python: >=3.6
Requires-Dist: backoff
Requires-Dist: boto3
Provides-Extra: pytest
Requires-Dist: pytest ; extra == 'pytest'
